odoo/addons/account_invoice_subscription_per_contact/README.rst
odoo/addons/account_invoice_subscription_per_contact/__init__.py
odoo/addons/account_invoice_subscription_per_contact/__manifest__.py
odoo/addons/account_invoice_subscription_per_contact/data/mail_message_subtype_data.xml
odoo/addons/account_invoice_subscription_per_contact/i18n/account_invoice_subscription_per_contact.pot
odoo/addons/account_invoice_subscription_per_contact/i18n/es.po
odoo/addons/account_invoice_subscription_per_contact/i18n/it.po
odoo/addons/account_invoice_subscription_per_contact/models/__init__.py
odoo/addons/account_invoice_subscription_per_contact/models/account_move.py
odoo/addons/account_invoice_subscription_per_contact/readme/CONTRIBUTORS.md
odoo/addons/account_invoice_subscription_per_contact/readme/DESCRIPTION.md
odoo/addons/account_invoice_subscription_per_contact/readme/USAGE.md
odoo/addons/account_invoice_subscription_per_contact/static/description/icon.png
odoo/addons/account_invoice_subscription_per_contact/static/description/index.html
odoo/addons/account_invoice_subscription_per_contact/tests/__init__.py
odoo/addons/account_invoice_subscription_per_contact/tests/test_account_invoice_subscription_per_contact.py
odoo_addon_account_invoice_subscription_per_contact-17.0.1.0.0.5.dist-info/METADATA
odoo_addon_account_invoice_subscription_per_contact-17.0.1.0.0.5.dist-info/WHEEL
odoo_addon_account_invoice_subscription_per_contact-17.0.1.0.0.5.dist-info/top_level.txt
odoo_addon_account_invoice_subscription_per_contact-17.0.1.0.0.5.dist-info/RECORD
